attr_sync_thing/__init__.py
attr_sync_thing/__main__.py
attr_sync_thing/attr_storage.py
attr_sync_thing/configuration.py
attr_sync_thing/file_info.py
attr_sync_thing/logging.py
attr_sync_thing/modification_manager.py
attr_sync_thing-0.4.dist-info/LICENSE
attr_sync_thing-0.4.dist-info/METADATA
attr_sync_thing-0.4.dist-info/WHEEL
attr_sync_thing-0.4.dist-info/entry_points.txt
attr_sync_thing-0.4.dist-info/top_level.txt
attr_sync_thing-0.4.dist-info/RECORD
