Metadata-Version: 2.1
Name: attr-sync-thing
Version: 0.4
Summary: Sync MacOS extended attributes through tools that do not support them (like nextCloud or ownCloud).
Author-email: Diedrich Vorberg <diedrich@tux4web.de>
Project-URL: Homepage, https://github.com/dvorberg/attr_sync_thing
Classifier: Programming Language :: Python :: 3
Classifier: License :: OSI Approved :: GNU General Public License v2 (GPLv2)
Classifier: Operating System :: MacOS :: MacOS X
License-File: LICENSE
Requires-Dist: watchdog
Requires-Dist: xattr
